n8n_chat_cli/__init__.py
n8n_chat_cli/cli.py
n8n_chat_cli-0.1.4.dist-info/licenses/LICENSE
n8n_chat_cli-0.1.4.dist-info/METADATA
n8n_chat_cli-0.1.4.dist-info/WHEEL
n8n_chat_cli-0.1.4.dist-info/entry_points.txt
n8n_chat_cli-0.1.4.dist-info/top_level.txt
n8n_chat_cli-0.1.4.dist-info/RECORD
