Metadata-Version: 2.4
Name: n8n-chat-cli
Version: 0.1.4
Summary: A command-line interface for n8n chat webhooks.
Author-email: Kuldip Satpute <satputekuldip@gmail.com>
Classifier: Programming Language :: Python :: 3
Classifier: License :: OSI Approved :: MIT License
Classifier: Operating System :: OS Independent
Requires-Python: >=3.8
License-File: LICENSE
Dynamic: license-file
